jupyterlite_scheme_kernel/__init__.py
jupyterlite_scheme_kernel/_version.py
jupyterlite_scheme_kernel/labextension/package.json
jupyterlite_scheme_kernel/labextension/static/509.66fcee67749a2454fd42.js
jupyterlite_scheme_kernel/labextension/static/7304cd91a65fd4c90a24.wasm
jupyterlite_scheme_kernel/labextension/static/873.564e360188311987ee35.js
jupyterlite_scheme_kernel/labextension/static/ab7c260ae908a2447af1.data
jupyterlite_scheme_kernel/labextension/static/remoteEntry.b55dd2b3c99fe17da4dd.js
jupyterlite_scheme_kernel/labextension/static/style.js
jupyterlite_scheme_kernel/labextension/static/third-party-licenses.json
jupyterlite_scheme_kernel_canary-0.4.1.data/data/share/jupyter/labextensions/jupyterlite-scheme-kernel/package.json
jupyterlite_scheme_kernel_canary-0.4.1.data/data/share/jupyter/labextensions/jupyterlite-scheme-kernel/static/509.66fcee67749a2454fd42.js
jupyterlite_scheme_kernel_canary-0.4.1.data/data/share/jupyter/labextensions/jupyterlite-scheme-kernel/static/7304cd91a65fd4c90a24.wasm
jupyterlite_scheme_kernel_canary-0.4.1.data/data/share/jupyter/labextensions/jupyterlite-scheme-kernel/static/873.564e360188311987ee35.js
jupyterlite_scheme_kernel_canary-0.4.1.data/data/share/jupyter/labextensions/jupyterlite-scheme-kernel/static/ab7c260ae908a2447af1.data
jupyterlite_scheme_kernel_canary-0.4.1.data/data/share/jupyter/labextensions/jupyterlite-scheme-kernel/static/remoteEntry.b55dd2b3c99fe17da4dd.js
jupyterlite_scheme_kernel_canary-0.4.1.data/data/share/jupyter/labextensions/jupyterlite-scheme-kernel/static/style.js
jupyterlite_scheme_kernel_canary-0.4.1.data/data/share/jupyter/labextensions/jupyterlite-scheme-kernel/static/third-party-licenses.json
jupyterlite_scheme_kernel_canary-0.4.1.dist-info/METADATA
jupyterlite_scheme_kernel_canary-0.4.1.dist-info/WHEEL
jupyterlite_scheme_kernel_canary-0.4.1.dist-info/entry_points.txt
jupyterlite_scheme_kernel_canary-0.4.1.dist-info/licenses/LICENSE
jupyterlite_scheme_kernel_canary-0.4.1.dist-info/RECORD
