Metadata-Version: 2.3
Name: jupyterlite-scheme-kernel-canary
Version: 0.4.1
Summary: A Scheme Kernel for JupyterLite using `ChezScheme`
Project-URL: Source, https://github.com/bencode/jupyterlite-scheme-kernel
Author-email: bencode <bencode@163.com>
License: MIT
Keywords: ChezScheme,jupyter,jupyterlab,jupyterlite,scheme
Classifier: Framework :: Jupyter
Classifier: Framework :: Jupyter :: JupyterLab
Classifier: Framework :: Jupyter :: JupyterLab :: 4
Classifier: License :: OSI Approved :: MIT License
Requires-Python: >=3.8
Requires-Dist: jupyterlite-core<0.5.0,>=0.4.0
